arcaea_offline/__init__.py
arcaea_offline/database.py
arcaea_offline/searcher.py
arcaea_offline/singleton.py
arcaea_offline/calculate/__init__.py
arcaea_offline/calculate/b30.py
arcaea_offline/calculate/score.py
arcaea_offline/calculate/world_step.py
arcaea_offline/external/__init__.py
arcaea_offline/external/andreal/__init__.py
arcaea_offline/external/andreal/account.py
arcaea_offline/external/andreal/api_data.py
arcaea_offline/external/arcaea/__init__.py
arcaea_offline/external/arcaea/common.py
arcaea_offline/external/arcaea/online.py
arcaea_offline/external/arcaea/packlist.py
arcaea_offline/external/arcaea/songlist.py
arcaea_offline/external/arcaea/st3.py
arcaea_offline/external/arcsong/__init__.py
arcaea_offline/external/arcsong/arcsong_db.py
arcaea_offline/external/arcsong/arcsong_json.py
arcaea_offline/external/chart_info_db/__init__.py
arcaea_offline/external/chart_info_db/parser.py
arcaea_offline/external/exports/__init__.py
arcaea_offline/external/exports/exporters.py
arcaea_offline/external/exports/types.py
arcaea_offline/external/smartrte/__init__.py
arcaea_offline/external/smartrte/b30_csv.py
arcaea_offline/models/__init__.py
arcaea_offline/models/common.py
arcaea_offline/models/config.py
arcaea_offline/models/scores.py
arcaea_offline/models/songs.py
arcaea_offline/utils/__init__.py
arcaea_offline/utils/partner.py
arcaea_offline/utils/rating.py
arcaea_offline/utils/score.py
arcaea_offline/utils/search_title.py
arcaea_offline-0.2.2.dist-info/LICENSE
arcaea_offline-0.2.2.dist-info/METADATA
arcaea_offline-0.2.2.dist-info/WHEEL
arcaea_offline-0.2.2.dist-info/top_level.txt
arcaea_offline-0.2.2.dist-info/RECORD
