Metadata-Version: 2.1
Name: arcaea-offline
Version: 0.2.2
Summary: Manage your local Arcaea score database.
Author-email: 283375 <log_283375@163.com>
Project-URL: Homepage, https://github.com/283375/arcaea-offline
Project-URL: Bug Tracker, https://github.com/283375/arcaea-offline/issues
Classifier: Development Status :: 3 - Alpha
Classifier: Programming Language :: Python :: 3
Requires-Python: >=3.8
License-File: LICENSE
Requires-Dist: beautifulsoup4 ==4.12.2
Requires-Dist: SQLAlchemy ==2.0.20
Requires-Dist: SQLAlchemy-Utils ==0.41.1
Requires-Dist: Whoosh ==2.7.4
